hwt/__init__.py
hwt/code.py
hwt/code_utils.py
hwt/constraints.py
hwt/doc_markers.py
hwt/math.py
hwt/hdl/__init__.py
hwt/hdl/constants.py
hwt/hdl/frameTmpl.py
hwt/hdl/frameTmplUtils.py
hwt/hdl/hdlObject.py
hwt/hdl/operator.py
hwt/hdl/operatorDefs.py
hwt/hdl/operatorUtils.py
hwt/hdl/portItem.py
hwt/hdl/sensitivityCtx.py
hwt/hdl/transPart.py
hwt/hdl/transTmpl.py
hwt/hdl/value.py
hwt/hdl/valueUtils.py
hwt/hdl/variables.py
hwt/hdl/statements/__init__.py
hwt/hdl/statements/assignmentContainer.py
hwt/hdl/statements/codeBlockContainer.py
hwt/hdl/statements/ifContainter.py
hwt/hdl/statements/statement.py
hwt/hdl/statements/switchContainer.py
hwt/hdl/statements/utils/__init__.py
hwt/hdl/statements/utils/comparison.py
hwt/hdl/statements/utils/ioDiscovery.py
hwt/hdl/statements/utils/reduction.py
hwt/hdl/statements/utils/signalCut.py
hwt/hdl/types/__init__.py
hwt/hdl/types/array.py
hwt/hdl/types/arrayCast.py
hwt/hdl/types/arrayVal.py
hwt/hdl/types/bitValFunctions.py
hwt/hdl/types/bitVal_opReduce.py
hwt/hdl/types/bits.py
hwt/hdl/types/bitsCast.py
hwt/hdl/types/bitsVal.py
hwt/hdl/types/defs.py
hwt/hdl/types/enum.py
hwt/hdl/types/enumVal.py
hwt/hdl/types/eventCapableVal.py
hwt/hdl/types/float.py
hwt/hdl/types/floatVal.py
hwt/hdl/types/hdlType.py
hwt/hdl/types/slice.py
hwt/hdl/types/sliceUtils.py
hwt/hdl/types/sliceVal.py
hwt/hdl/types/stream.py
hwt/hdl/types/streamVal.py
hwt/hdl/types/string.py
hwt/hdl/types/stringVal.py
hwt/hdl/types/struct.py
hwt/hdl/types/structCast.py
hwt/hdl/types/structUtils.py
hwt/hdl/types/structValBase.py
hwt/hdl/types/typeCast.py
hwt/hdl/types/union.py
hwt/hdl/types/utils.py
hwt/interfaces/__init__.py
hwt/interfaces/differential.py
hwt/interfaces/hsStructIntf.py
hwt/interfaces/intf_map.py
hwt/interfaces/signalOps.py
hwt/interfaces/std.py
hwt/interfaces/std_ip_defs.py
hwt/interfaces/structIntf.py
hwt/interfaces/tristate.py
hwt/interfaces/unionIntf.py
hwt/interfaces/utils.py
hwt/interfaces/agents/__init__.py
hwt/interfaces/agents/bramPort.py
hwt-3.8.dist-info/LICENSE
hwt-3.8.dist-info/METADATA
hwt-3.8.dist-info/WHEEL
hwt-3.8.dist-info/top_level.txt
hwt-3.8.dist-info/zip-safe
hwt-3.8.dist-info/RECORD
