Metadata-Version: 2.1
Name: hwt
Version: 3.8
Summary: hdl synthesis toolkit
Home-page: https://github.com/Nic30/hwt
Author: Michal Orsak
Author-email: Nic30original@gmail.com
License: MIT
Platform: UNKNOWN
Classifier: Development Status :: 4 - Beta
Classifier: Intended Audience :: Developers
Classifier: License :: OSI Approved :: MIT License
Classifier: Operating System :: OS Independent
Classifier: Programming Language :: Python :: 3 :: Only
Classifier: Programming Language :: Python :: 3
Classifier: Programming Language :: Python :: 3.6
Classifier: Programming Language :: Python :: 3.7
Classifier: Programming Language :: Python :: 3.8
Classifier: Programming Language :: Python :: 3.9
Classifier: Topic :: Scientific/Engineering :: Electronic Design Automation (EDA)
Classifier: Topic :: System :: Hardware
Classifier: Topic :: System :: Emulators
Classifier: Topic :: Utilities
License-File: LICENSE
Requires-Dist: hdlConvertorAst (>=1.0)
Requires-Dist: ipCorePackager (>=0.6)
Requires-Dist: hwtSimApi (>=1.3)
Requires-Dist: pyDigitalWaveTools (>=1.1)
